{"nodes": [{"id": "brainstorming_CollaborativeDesign", "label": "Collaborative Brainstorming Design", "file_type": "document", "source_file": "skills/recommended/brainstorming/SKILL.md", "source_location": null, "source_url": null, "captured_at": null, "author": null, "contributor": null}, {"id": "brainstorming_DesignApprovalGate", "label": "Design Approval Hard Gate", "file_type": "document", "source_file": "skills/recommended/brainstorming/SKILL.md", "source_location": "HARD-GATE block", "source_url": null, "captured_at": null, "author": null, "contributor": null}, {"id": "brainstorming_WritingPlansTransition", "label": "Brainstorming to Writing-Plans Transition", "file_type": "document", "source_file": "skills/recommended/brainstorming/SKILL.md", "source_location": "Process Flow and After the Design sections", "source_url": null, "captured_at": null, "author": null, "contributor": null}], "edges": [{"source": "brainstorming_DesignApprovalGate", "target": "brainstorming_CollaborativeDesign", "relation": "rationale_for", "confidence": "EXTRACTED", "confidence_score": 1.0, "source_file": "skills/recommended/brainstorming/SKILL.md", "source_location": "HARD-GATE block", "weight": 1.0}, {"source": "brainstorming_WritingPlansTransition", "target": "writing-plans_ImplementationPlanning", "relation": "references", "confidence": "EXTRACTED", "confidence_score": 1.0, "source_file": "skills/recommended/brainstorming/SKILL.md", "source_location": "Implementation section", "weight": 1.0}], "hyperedges": [{"nodes": ["brainstorming_CollaborativeDesign", "writing-plans_ImplementationPlanning", "planning-with-files_PlanningWithFiles"], "relation": "sequential_workflow", "confidence": "INFERRED", "confidence_score": 0.8, "source_file": "skills/recommended/brainstorming/SKILL.md", "weight": 0.8, "description": "Brainstorming produces a design doc, which transitions to writing-plans for implementation planning, which uses planning-with-files 3-file pattern for task tracking."}]}