{"nodes": [{"id": "\u672c\u5468\u6392\u671f_W20", "label": "W20 Weekly Schedule \u2014 Data Injection Focus", "file_type": "document", "source_file": "01-PERSONAL-OPS/02-PLANS-AND-SCHEDULES/\u672c\u5468\u6392\u671f.md", "source_location": null, "source_url": null, "captured_at": null, "author": null, "contributor": null}, {"id": "brain-os-5week-review_Concept", "label": "Brain OS 5-Week Review", "file_type": "document", "source_file": "01-PERSONAL-OPS/02-PLANS-AND-SCHEDULES/\u672c\u5468\u6392\u671f.md", "source_location": null, "source_url": null, "captured_at": null, "author": null, "contributor": null}, {"id": "conversation-mining-degraded_Concept", "label": "Conversation Mining Degraded (Volume Not Mounted)", "file_type": "document", "source_file": "01-PERSONAL-OPS/02-PLANS-AND-SCHEDULES/\u672c\u5468\u6392\u671f.md", "source_location": null, "source_url": null, "captured_at": null, "author": null, "contributor": null}], "edges": [{"source": "\u672c\u5468\u6392\u671f_W20", "target": "todo-backlog_Concept", "relation": "references", "confidence": "EXTRACTED", "confidence_score": 1.0, "source_file": "01-PERSONAL-OPS/02-PLANS-AND-SCHEDULES/\u672c\u5468\u6392\u671f.md", "source_location": null, "weight": 1.0}, {"source": "\u672c\u5468\u6392\u671f_W20", "target": "\u5f53\u524d\u627f\u8bfa\u4e8b\u9879_Concept", "relation": "references", "confidence": "EXTRACTED", "confidence_score": 1.0, "source_file": "01-PERSONAL-OPS/02-PLANS-AND-SCHEDULES/\u672c\u5468\u6392\u671f.md", "source_location": null, "weight": 1.0}, {"source": "\u672c\u5468\u6392\u671f_W20", "target": "progress-board_Concept", "relation": "references", "confidence": "EXTRACTED", "confidence_score": 1.0, "source_file": "01-PERSONAL-OPS/02-PLANS-AND-SCHEDULES/\u672c\u5468\u6392\u671f.md", "source_location": null, "weight": 1.0}, {"source": "\u672c\u5468\u6392\u671f_W20", "target": "decision-queue_Concept", "relation": "references", "confidence": "EXTRACTED", "confidence_score": 1.0, "source_file": "01-PERSONAL-OPS/02-PLANS-AND-SCHEDULES/\u672c\u5468\u6392\u671f.md", "source_location": null, "weight": 1.0}, {"source": "\u672c\u5468\u6392\u671f_W20", "target": "brain-os-5week-review_Concept", "relation": "references", "confidence": "EXTRACTED", "confidence_score": 1.0, "source_file": "01-PERSONAL-OPS/02-PLANS-AND-SCHEDULES/\u672c\u5468\u6392\u671f.md", "source_location": null, "weight": 1.0}, {"source": "\u672c\u5468\u6392\u671f_W20", "target": "conversation-mining-degraded_Concept", "relation": "references", "confidence": "EXTRACTED", "confidence_score": 1.0, "source_file": "01-PERSONAL-OPS/02-PLANS-AND-SCHEDULES/\u672c\u5468\u6392\u671f.md", "source_location": null, "weight": 1.0}], "hyperedges": []}